odoo/addons/mrp_planned_order_matrix/README.rst
odoo/addons/mrp_planned_order_matrix/__init__.py
odoo/addons/mrp_planned_order_matrix/__manifest__.py
odoo/addons/mrp_planned_order_matrix/i18n/mrp_planned_order_matrix.pot
odoo/addons/mrp_planned_order_matrix/i18n/pt_BR.po
odoo/addons/mrp_planned_order_matrix/readme/CONTRIBUTORS.rst
odoo/addons/mrp_planned_order_matrix/readme/DESCRIPTION.rst
odoo/addons/mrp_planned_order_matrix/readme/INSTALL.rst
odoo/addons/mrp_planned_order_matrix/readme/USAGE.rst
odoo/addons/mrp_planned_order_matrix/static/description/icon.png
odoo/addons/mrp_planned_order_matrix/static/description/index.html
odoo/addons/mrp_planned_order_matrix/tests/__init__.py
odoo/addons/mrp_planned_order_matrix/tests/test_mrp_planned_order_matrix.py
odoo/addons/mrp_planned_order_matrix/wizards/__init__.py
odoo/addons/mrp_planned_order_matrix/wizards/mrp_planned_order_wizard.py
odoo/addons/mrp_planned_order_matrix/wizards/mrp_planned_order_wizard_view.xml
odoo12_addon_mrp_planned_order_matrix-12.0.1.0.2.dist-info/METADATA
odoo12_addon_mrp_planned_order_matrix-12.0.1.0.2.dist-info/WHEEL
odoo12_addon_mrp_planned_order_matrix-12.0.1.0.2.dist-info/top_level.txt
odoo12_addon_mrp_planned_order_matrix-12.0.1.0.2.dist-info/RECORD
