Metadata-Version: 2.1
Name: odoo12-addon-mrp-planned-order-matrix
Version: 12.0.1.0.2
Summary: Allows to create fixed planned orders on a grid view.
Home-page: https://github.com/OCA/manufacture
Author: ForgeFlow, Odoo Community Association (OCA)
Author-email: support@odoo-community.org
License: AGPL-3
Platform: UNKNOWN
Classifier: Programming Language :: Python
Classifier: Framework :: Odoo
Classifier: Framework :: Odoo :: 12.0
Classifier: License :: OSI Approved :: GNU Affero General Public License v3
Requires-Python: >=3.5
Requires-Dist: odoo12-addon-date-range
Requires-Dist: odoo12-addon-mrp-multi-level
Requires-Dist: odoo12-addon-web-widget-x2many-2d-matrix
Requires-Dist: odoo (<12.1dev,>=12.0a)
